code/102003704.py
code/__init__.py
Topsis_Vishakhaa_102003704-1.0.4.dist-info/LICENSE.txt
Topsis_Vishakhaa_102003704-1.0.4.dist-info/METADATA
Topsis_Vishakhaa_102003704-1.0.4.dist-info/WHEEL
Topsis_Vishakhaa_102003704-1.0.4.dist-info/entry_points.txt
Topsis_Vishakhaa_102003704-1.0.4.dist-info/top_level.txt
Topsis_Vishakhaa_102003704-1.0.4.dist-info/RECORD
